google_services_helper-1.0.3.dist-info/METADATA
google_services_helper-1.0.3.dist-info/RECORD
google_services_helper-1.0.3.dist-info/WHEEL
google_services_helper-1.0.3.dist-info/top_level.txt
vedavaapi/__init__.py
vedavaapi/google_helper/__init__.py
vedavaapi/google_helper/factory.py
vedavaapi/google_helper/gdrive/__init__.py
vedavaapi/google_helper/gdrive/helper.py
vedavaapi/google_helper/gsheets/__init__.py
vedavaapi/google_helper/gsheets/helper.py
vedavaapi/google_helper/oauth/__init__.py
vedavaapi/google_helper/oauth/authorization_helper.py
vedavaapi/google_helper/oauth/creds_helper.py
