Metadata-Version: 2.1
Name: google-services-helper
Version: 1.0.3
Summary: google api helper for vedavaapi project
Home-page: https://github.com/vedavaapi
Author: vedavaapi
Author-email: vvsvmb151@gmail.com
License: UNKNOWN
Platform: UNKNOWN
Classifier: Programming Language :: Python :: 2.7
Classifier: Operating System :: OS Independent
Requires-Dist: flask
Requires-Dist: google-auth
Requires-Dist: google-auth-oauthlib
Requires-Dist: google-auth-httplib2
Requires-Dist: google-api-python-client
